{
    "isReadOnly": false,
    "commitMode": "Immediate",
    "validationMode": "Immediate",
    "propertyAnnotations":
    [
        {
            "name": "first_name",
            "displayName": "First Name",
            "index": 0,
            "required": true
        },
        {
            "name": "last_name",
            "displayName": "Last Name",
            "index": 1,
            "required": true
		},
        {
            "name": "date_of_birth",
            "displayName": "Date of Birth",
            "index": 2,
            "editor": "DatePicker",
            "required": true,
            "strokeColor": "black"
		},
		{
            "name": "gender",
            "displayName": "Gender",
            "index": 3,
            "required": true,
            "editor": "Picker",
            "valuesProvider": ["Male","Female","Other"]
        },
        {
            "name": "assigned_children_number",
            "displayName": "Assigned Children",
            "index": 4,
            "required": true,
            "editor": "Number"
        },
        {
            "name": "assigned_office_name",
            "displayName": "Assigned Office",
            "index": 5,
            "required": true
        },
        {
            "name": "village_name",
            "displayName": "Village",
            "index": 6,
            "required": true
        },
        {
            "name": "deanery_name",
            "displayName": "Deanery",
            "index": 7,
            "required": true
        },
        {
            "name": "diocese_name",
            "displayName": "Diocese",
            "index": 8,
            "required": true
        },
        {
            "name": "parish_worker_name",
            "displayName": "Parish Worker",
            "index": 9,
            "required": true
        },
        {
            "name": "social_worker_name",
            "displayName": "Social Worker",
            "index": 10,
            "required": true
        },
        {
            "name": "receiving_money",
            "displayName": "Receiving Money?",
            "index": 11,
            "editor": "Switch",
            "required": true
        },
        {
            "name": "assigned_sponsor_name",
            "displayName": "Assigned Sponsor",
            "index": 12,
            "required": true
        },
        {
            "name": "verified_by_guernsey",
            "displayName": "Verified By Guernsey?",
            "index": 13,
            "editor": "Switch",
            "required": true
        },
        {
            "name": "date_verified",
            "displayName": "Date Verified",
            "index": 14,
            "editor": "DatePicker",
            "required": true,
            "strokeColor": "black"
		},
		{
            "name": "house_type_name",
            "displayName": "House Type",
            "index": 15,
            "required": true
        },
        {
            "name": "house_provided",
            "displayName": "House Provided?",
			"index": 16,
			"editor": "Switch",
            "required": true
        },
        {
            "name": "diet_type_name",
            "displayName": "Diet Type",
            "index": 17,
            "required": true
        },
        {
            "name": "food_needs",
            "displayName": "Food Needs",
            "index": 18,
            "required": true
        },
        {
            "name": "work_type_name",
            "displayName": "Work Type",
            "index": 19,
            "required": true
        },
        {
            "name": "distance_to_work",
            "displayName": "Distance To Work (Km)",
			"index": 20,
			"editor":"Number",
            "required": true
        },
        {
            "name": "created_by",
            "displayName": "Record Creator",
			"required": true,
			"ignore":true
        },
        {
            "name": "nearest_hospital_name",
            "displayName": "Nearest Hospital",
            "index": 21,
            "required": true
        },
        {
            "name": "distance_to_hospital",
            "displayName": "Distance To Hospital (Km)",
			"index":22,
			"editor":"Number",
            "required": true
        },
        {
            "name": "water_type_name",
            "displayName": "Water Type",
            "index": 23,
            "required": true
        },
        {
            "name": "distance_to_water",
            "displayName": "Distance To Water (Km)",
            "index": 24,
            "editor": "Number",
            "required": true
        },
        {
            "name": "situation",
            "displayName": "Situation",
			"index": 25,
			"editor": "MultilineText",
            "required": true
        },
        {
            "name": "assigned_children",
            "ignore":true,
            "required": true
        },
        {
            "name": "assigned_office",
            "ignore":true,
            "required": true
        },
        {
            "name": "village",
            "ignore": true,
            "required": true
        },
        {
            "name": "deanery",
            "ignore": true,
            "required": true
        },
        {
            "name": "diocese",
            "ignore": true,
            "required": true
        },
        {
            "name": "image",
            "ignore": true,
            "required": true
		},
		{
            "name": "parish_worker",
            "ignore":true,
            "required": true
        },
        {
            "name": "social_worker",
            "ignore":true,
            "required": true
        },
        {
            "name": "assigned_sponsor",
            "ignore": true,
            "required": true
        },
        {
            "name": "house_type",
            "ignore": true,
            "required": true
        },
        {
            "name": "diet_type",
            "ignore": true,
            "required": true
        },
        {
            "name": "work_type",
            "ignore": true,
            "required": true
        },
        {
            "name": "nearest_hospital",
            "ignore": true,
            "required": true
        },
        {
            "name": "water_type",
            "ignore": true,
            "required": true
		},
		{
			"name": "id",
			"ignore":true,
			"required":true
		},
		{
			"name": "age",
			"ignore": true,
			"required":true
		}
    ]
}